README.md
setup.cfg
setup.py
pretrainedmodels/__init__.py
pretrainedmodels/utils.py
pretrainedmodels/version.py
pretrainedmodels.egg-info/PKG-INFO
pretrainedmodels.egg-info/SOURCES.txt
pretrainedmodels.egg-info/dependency_links.txt
pretrainedmodels.egg-info/requires.txt
pretrainedmodels.egg-info/top_level.txt
pretrainedmodels/datasets/__init__.py
pretrainedmodels/datasets/utils.py
pretrainedmodels/datasets/voc.py
pretrainedmodels/models/__init__.py
pretrainedmodels/models/bninception.py
pretrainedmodels/models/cafferesnet.py
pretrainedmodels/models/dpn.py
pretrainedmodels/models/fbresnet.py
pretrainedmodels/models/inceptionresnetv2.py
pretrainedmodels/models/inceptionv4.py
pretrainedmodels/models/nasnet.py
pretrainedmodels/models/nasnet_mobile.py
pretrainedmodels/models/resnext.py
pretrainedmodels/models/senet.py
pretrainedmodels/models/torchvision_models.py
pretrainedmodels/models/utils.py
pretrainedmodels/models/vggm.py
pretrainedmodels/models/wideresnet.py
pretrainedmodels/models/xception.py
pretrainedmodels/models/resnext_features/__init__.py
pretrainedmodels/models/resnext_features/resnext101_32x4d_features.py
pretrainedmodels/models/resnext_features/resnext101_64x4d_features.py