Metadata-Version: 1.1
Name: pretrainedmodels
Version: 0.6.1
Summary: Pretrained models for Pytorch
Home-page: https://github.com/cadene/pretrained-models.pytorch
Author: Remi Cadene
Author-email: remi.cadene@icloud.com
License: UNKNOWN
Keywords: pytorch pretrained models deep learning
Platform: UNKNOWN
Classifier: Development Status :: 3 - Alpha
Classifier: Intended Audience :: Developers
Classifier: Topic :: Software Development :: Build Tools
Classifier: License :: OSI Approved :: MIT License
Classifier: Programming Language :: Python :: 3.6
